badges/__init__.py
badges/apps.py
badges/urls.py
badges/views.py
badges/static/badges.scss
badges/static/vendor/normalize.css/normalize.css
badges/templates/badges/base_badge.html
badges/templates/badges/single_badge.html
badges/templates/badges/snippets/bottom.html
badges/templates/badges/snippets/full.html
badges/templates/badges/snippets/midleft.html
badges/templates/badges/snippets/midright.html
badges/templates/badges/snippets/top.html
bursary/__init__.py
bursary/admin.py
bursary/apps.py
bursary/forms.py
bursary/models.py
bursary/tests.py
bursary/urls.py
bursary/views.py
bursary/management/__init__.py
bursary/management/commands/__init__.py
bursary/management/commands/badger_travel_bursaries.py
bursary/management/commands/cancel_unable_travel_without_bursary.py
bursary/management/commands/issue_invoice_without_bursary.py
bursary/migrations/0001_initial.py
bursary/migrations/0002_update_fk.py
bursary/migrations/0003_add_expense_request.py
bursary/migrations/0004_bursary_attendance_status.py
bursary/migrations/0005_alter_bursary_options_bursary_partial_contribution.py
bursary/migrations/0006_bursary_budget.py
bursary/migrations/__init__.py
bursary/templates/bursary/notify_attendance_status.txt
bursary/templates/bursary/notify_status.txt
bursary/templates/bursary/update.html
daytrip/__init__.py
daytrip/admin.py
daytrip/apps.py
daytrip/forms.py
daytrip/models.py
daytrip/urls.py
daytrip/views.py
daytrip/migrations/0001_initial.py
daytrip/migrations/__init__.py
daytrip/templates/daytrip/daytrip.html
daytrip/templates/daytrip/travelinsurance_form.html
debconf/__init__.py
debconf/common_settings.py
debconf/context_processors.py
debconf/countries.py
debconf/models.py
debconf/settings.py
debconf/talk_urls.py
debconf/tz.py
debconf/urls.py
debconf/views.py
debconf/locale/django.pot
debconf/locale/pt_BR/LC_MESSAGES/django.mo
debconf/locale/pt_BR/LC_MESSAGES/django.po
debconf/management/__init__.py
debconf/management/commands/__init__.py
wafer_debconf-0.17.0.dist-info/licenses/LICENSE
wafer_debconf-0.17.0.dist-info/METADATA
wafer_debconf-0.17.0.dist-info/WHEEL
wafer_debconf-0.17.0.dist-info/top_level.txt
wafer_debconf-0.17.0.dist-info/RECORD
