Metadata-Version: 2.4
Name: wafer-debconf
Version: 0.17.0
Summary: Wafer extensions used by DebConf
Home-page: https://salsa.debian.org/debconf-team/public/websites/wafer-debconf
Author: DebConf Team
Author-email: debconf-team@lists.debian.org
Classifier: Development Status :: 4 - Beta
Classifier: Framework :: Django
Classifier: License :: OSI Approved :: ISC License (ISCL)
Classifier: Programming Language :: Python :: 3 :: Only
Classifier: Topic :: Communications :: Conferencing
License-File: LICENSE
Requires-Dist: mdx_linkify
Requires-Dist: wafer<0.17,>=0.16
Requires-Dist: mdx_staticfiles
Requires-Dist: Django<5,>=3
Requires-Dist: django_compressor
Requires-Dist: django_countries
Requires-Dist: django_extensions
Requires-Dist: django_libsass
Dynamic: author
Dynamic: author-email
Dynamic: classifier
Dynamic: description
Dynamic: description-content-type
Dynamic: home-page
Dynamic: license-file
Dynamic: requires-dist
Dynamic: summary
